{"files":{"packages/shared-utils/dist/response.util.d.ts.map":{"size":586,"mtime_nanos":1776439839368012999,"mode":420,"is_dir":false},"packages/shared-utils/dist/verify.js":{"size":3289,"mtime_nanos":1776439604256269458,"mode":420,"is_dir":false},"packages/shared-utils/dist/jwt.util.js":{"size":2281,"mtime_nanos":1776439714749756390,"mode":420,"is_dir":false},"packages/shared-utils/dist":{"size":0,"mtime_nanos":0,"mode":0,"is_dir":true},"packages/shared-utils/dist/validate.util.d.ts":{"size":489,"mtime_nanos":1776439604264839336,"mode":420,"is_dir":false},"packages/shared-utils/dist/response.util.d.ts":{"size":607,"mtime_nanos":1776439604263587479,"mode":420,"is_dir":false},"packages/shared-utils/dist/jwt.util.js.map":{"size":604,"mtime_nanos":1776439714749550476,"mode":420,"is_dir":false},"packages/shared-utils/dist/response.util.js":{"size":967,"mtime_nanos":1776439839367425299,"mode":420,"is_dir":false},"packages/shared-utils/dist/crypto.util.js.map":{"size":1765,"mtime_nanos":1776439604250804578,"mode":420,"is_dir":false},"packages/shared-utils/dist/validate.util.js.map":{"size":713,"mtime_nanos":1776439604264416717,"mode":420,"is_dir":false},"packages/shared-utils/dist/verify.js.map":{"size":2513,"mtime_nanos":1776439604256059545,"mode":420,"is_dir":false},"packages/shared-utils/dist/date.util.d.ts":{"size":1046,"mtime_nanos":1776439604260285776,"mode":420,"is_dir":false},"packages/shared-utils/dist/date.util.js.map":{"size":1674,"mtime_nanos":1776439604259426705,"mode":420,"is_dir":false},"packages/shared-utils/dist/validate.util.js":{"size":1023,"mtime_nanos":1776439604264496341,"mode":420,"is_dir":false},"packages/shared-utils/dist/verify.d.ts.map":{"size":106,"mtime_nanos":1776439604256684411,"mode":420,"is_dir":false},"packages/shared-utils/dist/crypto.util.js":{"size":3408,"mtime_nanos":1776439604250945868,"mode":420,"is_dir":false},"packages/shared-utils/dist/index.js":{"size":1034,"mtime_nanos":1776439714751512240,"mode":420,"is_dir":false},"packages/shared-utils/dist/jwt.util.d.ts":{"size":720,"mtime_nanos":1776439714750552629,"mode":420,"is_dir":false},"packages/shared-utils/dist/validate.util.d.ts.map":{"size":349,"mtime_nanos":1776439604264748545,"mode":420,"is_dir":false},"packages/shared-utils/dist/index.js.map":{"size":181,"mtime_nanos":1776439714751424450,"mode":420,"is_dir":false},"packages/shared-utils/dist/crypto.util.d.ts":{"size":886,"mtime_nanos":1776439604251826397,"mode":420,"is_dir":false},"packages/shared-utils/dist/response.util.js.map":{"size":686,"mtime_nanos":1776439839367328134,"mode":420,"is_dir":false},"packages/shared-utils/.turbo/turbo-build.log":{"size":51,"mtime_nanos":1776439839382354669,"mode":420,"is_dir":false},"packages/shared-utils/dist/date.util.d.ts.map":{"size":530,"mtime_nanos":1776439604260135445,"mode":420,"is_dir":false},"packages/shared-utils/dist/crypto.util.d.ts.map":{"size":468,"mtime_nanos":1776439604251510193,"mode":420,"is_dir":false},"packages/shared-utils/dist/verify.d.ts":{"size":47,"mtime_nanos":1776439604256927282,"mode":420,"is_dir":false},"packages/shared-utils/dist/date.util.js":{"size":2280,"mtime_nanos":1776439604259552828,"mode":420,"is_dir":false},"packages/shared-utils/dist/index.d.ts":{"size":189,"mtime_nanos":1776439604253233293,"mode":420,"is_dir":false},"packages/shared-utils/dist/jwt.util.d.ts.map":{"size":463,"mtime_nanos":1776439714750423506,"mode":420,"is_dir":false},"packages/shared-utils/dist/index.d.ts.map":{"size":211,"mtime_nanos":1776439839362802573,"mode":420,"is_dir":false}},"order":["packages/shared-utils/.turbo/turbo-build.log","packages/shared-utils/dist","packages/shared-utils/dist/crypto.util.d.ts","packages/shared-utils/dist/crypto.util.d.ts.map","packages/shared-utils/dist/crypto.util.js","packages/shared-utils/dist/crypto.util.js.map","packages/shared-utils/dist/date.util.d.ts","packages/shared-utils/dist/date.util.d.ts.map","packages/shared-utils/dist/date.util.js","packages/shared-utils/dist/date.util.js.map","packages/shared-utils/dist/index.d.ts","packages/shared-utils/dist/index.d.ts.map","packages/shared-utils/dist/index.js","packages/shared-utils/dist/index.js.map","packages/shared-utils/dist/jwt.util.d.ts","packages/shared-utils/dist/jwt.util.d.ts.map","packages/shared-utils/dist/jwt.util.js","packages/shared-utils/dist/jwt.util.js.map","packages/shared-utils/dist/response.util.d.ts","packages/shared-utils/dist/response.util.d.ts.map","packages/shared-utils/dist/response.util.js","packages/shared-utils/dist/response.util.js.map","packages/shared-utils/dist/validate.util.d.ts","packages/shared-utils/dist/validate.util.d.ts.map","packages/shared-utils/dist/validate.util.js","packages/shared-utils/dist/validate.util.js.map","packages/shared-utils/dist/verify.d.ts","packages/shared-utils/dist/verify.d.ts.map","packages/shared-utils/dist/verify.js","packages/shared-utils/dist/verify.js.map"]}